yaphs/__init__.py
yaphs-1.0.dist-info/LICENSE
yaphs-1.0.dist-info/METADATA
yaphs-1.0.dist-info/WHEEL
yaphs-1.0.dist-info/top_level.txt
yaphs-1.0.dist-info/RECORD
