Metadata-Version: 2.1
Name: yaphs
Version: 1.0
Summary: Yet another python hook system
Home-page: https://gitlab.com/valtrok/yaphs
Author: Corentin CAM
Author-email: cam.corentin@gmail.com
License: UNKNOWN
Project-URL: Source Code, https://gitlab.com/valtrok/yaphs
Platform: UNKNOWN
Classifier: Programming Language :: Python :: 2.7
Classifier: Programming Language :: Python :: 3
Classifier: License :: OSI Approved :: MIT License
Classifier: Operating System :: OS Independent
